pisa_internal/__init__.py
pisa_internal/__main__.py
pisa_internal/mcp.py
pisa_internal-0.1.0.dist-info/METADATA
pisa_internal-0.1.0.dist-info/WHEEL
pisa_internal-0.1.0.dist-info/entry_points.txt
pisa_internal-0.1.0.dist-info/top_level.txt
pisa_internal-0.1.0.dist-info/RECORD
